{
"type": "FeatureCollection",
"name": "space needle",
"crs": { "type": "name", "properties": { "name": "urn:ogc:def:crs:OGC:1.3:CRS84" } },
"features": [
{ "type": "Feature", "properties": { "id": 1 }, "geometry": { "type": "Point", "coordinates": [ -122.349291541319971, 47.620562300912347 ] } }
]
}
